<?xml version="1.0" encoding="utf-8"?>
<?xml-stylesheet type='text/xsl' href='../../rpt.xslt'?>
<CONTRIBUTIONDISCLOSURE>
  <filerType>O</filerType>
  <organizationName>FARMERS GROUP, INC</organizationName>
  <lobbyistPrefix>
  </lobbyistPrefix>
  <lobbyistFirstName>
  </lobbyistFirstName>
  <lobbyistMiddleName>
  </lobbyistMiddleName>
  <lobbyistLastName>
  </lobbyistLastName>
  <lobbyistSuffix>
  </lobbyistSuffix>
  <lobbyistID>
  </lobbyistID>
  <address2>
  </address2>
  <zipext>
  </zipext>
  <contactName>RUDY TREVINO</contactName>
  <senateRegID>49910</senateRegID>
  <houseRegID>34650</houseRegID>
  <reportYear>2019</reportYear>
  <reportType>YY</reportType>
  <amendment>False</amendment>
  <comments>
  </comments>
  <signedDate>1/27/2020 8:43:00 PM</signedDate>
  <certifiedcontent>true</certifiedcontent>
  <noContributions>false</noContributions>
  <pacs>
    <pac>
      <name>FARMERS GROUP, INC. POLITICAL ACTION COMMITTEE</name>
    </pac>
  </pacs>
  <contributions>
    <contribution>
      <type>FECA</type>
      <contributorName>FARMERS GROUP, INC. POLITICAL ACTION COMMITTEE</contributorName>
      <payeeName>ANN WAGNER FOR CONGRESS</payeeName>
      <recipientName>REP. ANN WAGNER</recipientName>
      <amount>2000</amount>
      <date>9/26/2019</date>
    </contribution>
    <contribution>
      <type>FECA</type>
      <contributorName>FARMERS GROUP, INC. POLITICAL ACTION COMMITTEE</contributorName>
      <payeeName>CHUY GARCIA FOR CONGRESS</payeeName>
      <recipientName>REP. JESUS GARCIA</recipientName>
      <amount>1000</amount>
      <date>9/26/2019</date>
    </contribution>
    <contribution>
      <type>FECA</type>
      <contributorName>FARMERS GROUP, INC. POLITICAL ACTION COMMITTEE</contributorName>
      <payeeName>CONOR LAMB FOR CONGRESS</payeeName>
      <recipientName>REP. CONOR LAMB</recipientName>
      <amount>1000</amount>
      <date>9/26/2019</date>
    </contribution>
    <contribution>
      <type>FECA</type>
      <contributorName>FARMERS GROUP, INC. POLITICAL ACTION COMMITTEE</contributorName>
      <payeeName>DENNY HECK FOR CONGRESS</payeeName>
      <recipientName>REP. DENNIS HECK</recipientName>
      <amount>2000</amount>
      <date>9/26/2019</date>
    </contribution>
    <contribution>
      <type>FECA</type>
      <contributorName>FARMERS GROUP, INC. POLITICAL ACTION COMMITTEE</contributorName>
      <payeeName>EMMER FOR CONGRESS</payeeName>
      <recipientName>REP. THOMAS EMMER</recipientName>
      <amount>2500</amount>
      <date>9/26/2019</date>
    </contribution>
    <contribution>
      <type>FECA</type>
      <contributorName>FARMERS GROUP, INC. POLITICAL ACTION COMMITTEE</contributorName>
      <payeeName>HOYER FOR CONGRESS</payeeName>
      <recipientName>REP. STENY H HOYER</recipientName>
      <amount>2500</amount>
      <date>9/26/2019</date>
    </contribution>
    <contribution>
      <type>FECA</type>
      <contributorName>FARMERS GROUP, INC. POLITICAL ACTION COMMITTEE</contributorName>
      <payeeName>JASON CROW FOR CONGRESS</payeeName>
      <recipientName>REP. JASON CROW</recipientName>
      <amount>1000</amount>
      <date>9/26/2019</date>
    </contribution>
    <contribution>
      <type>FECA</type>
      <contributorName>FARMERS GROUP, INC. POLITICAL ACTION COMMITTEE</contributorName>
      <payeeName>JEFFRIES FOR CONGRESS</payeeName>
      <recipientName>REP. HAKEEM JEFFRIES</recipientName>
      <amount>2500</amount>
      <date>9/26/2019</date>
    </contribution>
    <contribution>
      <type>FECA</type>
      <contributorName>FARMERS GROUP, INC. POLITICAL ACTION COMMITTEE</contributorName>
      <payeeName>PROJECT WEST POLITICAL ACTION COMMITTEE</payeeName>
      <recipientName>SEN. CORY GARDNER</recipientName>
      <amount>5000</amount>
      <date>9/26/2019</date>
    </contribution>
    <contribution>
      <type>FECA</type>
      <contributorName>FARMERS GROUP, INC. POLITICAL ACTION COMMITTEE</contributorName>
      <payeeName>TREY FOR CONGRESS</payeeName>
      <recipientName>REP. TREY HOLLINGSWORTH</recipientName>
      <amount>2000</amount>
      <date>9/26/2019</date>
    </contribution>
    <contribution>
      <type>FECA</type>
      <contributorName>FARMERS GROUP, INC. POLITICAL ACTION COMMITTEE</contributorName>
      <payeeName>WILLIAM TIMMONS FOR CONGRESS</payeeName>
      <recipientName>REP. WILLIAM TIMMONS</recipientName>
      <amount>1500</amount>
      <date>9/26/2019</date>
    </contribution>
    <contribution>
      <type>FECA</type>
      <contributorName>FARMERS GROUP, INC. POLITICAL ACTION COMMITTEE</contributorName>
      <payeeName>ZELDIN FOR CONGRESS</payeeName>
      <recipientName>REP. LEE ZELDIN</recipientName>
      <amount>1000</amount>
      <date>9/26/2019</date>
    </contribution>
    <contribution>
      <type>FECA</type>
      <contributorName>FARMERS GROUP, INC. POLITICAL ACTION COMMITTEE</contributorName>
      <payeeName>UPPER HAND FUND</payeeName>
      <recipientName>REP.'S BILL HUIZENGA, ANDY BARR, PATRICK MCHENRY, ANN WAGNER, SEAN DUFFY, BLAINE LEUTKEMEYER, FRENCH HILL, STEVE STIVERS, BRAD WENSTRUP, REPUBLICAN PARTY OF WISCONSIN AND KENTUCKY (FEDERAL ACCOUNTS), REPUBLICAN FINANCE COMMITTEE OF HAMILTON COUNTY (FEDERAL ACCOUNT) AND NRCC</recipientName>
      <amount>5000</amount>
      <date>9/26/2019</date>
    </contribution>
    <contribution>
      <type>FECA</type>
      <contributorName>FARMERS GROUP, INC. POLITICAL ACTION COMMITTEE</contributorName>
      <payeeName>BRIAN FITZPATRICK FOR CONGRESS</payeeName>
      <recipientName>REP. BRIAN FITZPATRICK</recipientName>
      <amount>5000</amount>
      <date>11/11/2019</date>
    </contribution>
    <contribution>
      <type>FECA</type>
      <contributorName>FARMERS GROUP, INC. POLITICAL ACTION COMMITTEE</contributorName>
      <payeeName>FRIENDS OF DENVER RIGGLEMAN, INC.</payeeName>
      <recipientName>REP. DENVER RIGGLEMAN</recipientName>
      <amount>2000</amount>
      <date>11/11/2019</date>
    </contribution>
    <contribution>
      <type>FECA</type>
      <contributorName>FARMERS GROUP, INC. POLITICAL ACTION COMMITTEE</contributorName>
      <payeeName>WENSTRUP FOR CONGRESS</payeeName>
      <recipientName>REP. BRAD WENSTRUP</recipientName>
      <amount>2000</amount>
      <date>11/11/2019</date>
    </contribution>
    <contribution>
      <type>FECA</type>
      <contributorName>FARMERS GROUP, INC. POLITICAL ACTION COMMITTEE</contributorName>
      <payeeName>TED LIEU FOR CONGRESS</payeeName>
      <recipientName>REP. TED LIEU</recipientName>
      <amount>2000</amount>
      <date>11/11/2019</date>
    </contribution>
    <contribution>
      <type>FECA</type>
      <contributorName>FARMERS GROUP, INC. POLITICAL ACTION COMMITTEE</contributorName>
      <payeeName>HUDSON FOR CONGRESS</payeeName>
      <recipientName>REP. RICHARD HUDSON</recipientName>
      <amount>2500</amount>
      <date>11/11/2019</date>
    </contribution>
    <contribution>
      <type>FECA</type>
      <contributorName>FARMERS GROUP, INC. POLITICAL ACTION COMMITTEE</contributorName>
      <payeeName>PEOPLE FOR DEREK KILMER</payeeName>
      <recipientName>REP. DEREK KILMER</recipientName>
      <amount>2500</amount>
      <date>11/11/2019</date>
    </contribution>
    <contribution>
      <type>FECA</type>
      <contributorName>FARMERS GROUP, INC. POLITICAL ACTION COMMITTEE</contributorName>
      <payeeName>ZELDIN FOR CONGRESS</payeeName>
      <recipientName>REP. LEE ZELDIN</recipientName>
      <amount>2500</amount>
      <date>11/11/2019</date>
    </contribution>
    <contribution>
      <type>FECA</type>
      <contributorName>FARMERS GROUP, INC. POLITICAL ACTION COMMITTEE</contributorName>
      <payeeName>ANDY BARR FOR CONGRESS, INC.</payeeName>
      <recipientName>REP. ANDY BARR</recipientName>
      <amount>1000</amount>
      <date>12/16/2019</date>
    </contribution>
    <contribution>
      <type>FECA</type>
      <contributorName>FARMERS GROUP, INC. POLITICAL ACTION COMMITTEE</contributorName>
      <payeeName>DON BACON FOR CONGRESS</payeeName>
      <recipientName>REP. DONALD J. BACON</recipientName>
      <amount>1000</amount>
      <date>12/16/2019</date>
    </contribution>
    <contribution>
      <type>FECA</type>
      <contributorName>FARMERS GROUP, INC. POLITICAL ACTION COMMITTEE</contributorName>
      <payeeName>E-PAC</payeeName>
      <recipientName>REP. ELISE M. STEFANIK</recipientName>
      <amount>5000</amount>
      <date>12/16/2019</date>
    </contribution>
    <contribution>
      <type>FECA</type>
      <contributorName>FARMERS GROUP, INC. POLITICAL ACTION COMMITTEE</contributorName>
      <payeeName>ELISE FOR CONGRESS</payeeName>
      <recipientName>REP. ELISE M. STEFANIK</recipientName>
      <amount>1000</amount>
      <date>12/16/2019</date>
    </contribution>
    <contribution>
      <type>FECA</type>
      <contributorName>FARMERS GROUP, INC. POLITICAL ACTION COMMITTEE</contributorName>
      <payeeName>FRIENDS OF JIM INHOFE</payeeName>
      <recipientName>SEN. JIM INHOFE</recipientName>
      <amount>1000</amount>
      <date>12/16/2019</date>
    </contribution>
    <contribution>
      <type>FECA</type>
      <contributorName>FARMERS GROUP, INC. POLITICAL ACTION COMMITTEE</contributorName>
      <payeeName>JIMMY PANETTA FOR CONGRESS</payeeName>
      <recipientName>REP. JIMMY PANETTA</recipientName>
      <amount>2500</amount>
      <date>12/16/2019</date>
    </contribution>
    <contribution>
      <type>FECA</type>
      <contributorName>FARMERS GROUP, INC. POLITICAL ACTION COMMITTEE</contributorName>
      <payeeName>MCHENRY FOR CONGRESS</payeeName>
      <recipientName>REP. PATRICK MCHENRY</recipientName>
      <amount>2500</amount>
      <date>12/16/2019</date>
    </contribution>
    <contribution>
      <type>FECA</type>
      <contributorName>FARMERS GROUP, INC. POLITICAL ACTION COMMITTEE</contributorName>
      <payeeName>SOUTHERN CALIFORNIA FUND</payeeName>
      <recipientName>REP. BRAD SHERMAN</recipientName>
      <amount>2500</amount>
      <date>12/16/2019</date>
    </contribution>
    <contribution>
      <type>FECA</type>
      <contributorName>FARMERS GROUP, INC. POLITICAL ACTION COMMITTEE</contributorName>
      <payeeName>MCSALLY FOR SENATE INC.</payeeName>
      <recipientName>SEN. MARTHA MCSALLY</recipientName>
      <amount>1500</amount>
      <date>12/16/2019</date>
    </contribution>
    <contribution>
      <type>FECA</type>
      <contributorName>FARMERS GROUP, INC. POLITICAL ACTION COMMITTEE</contributorName>
      <payeeName>MCSALLY FOR SENATE INC.</payeeName>
      <recipientName>SEN. MARTHA MCSALLY</recipientName>
      <amount>500</amount>
      <date>12/16/2019</date>
    </contribution>
    <contribution>
      <type>Honorary Expenses</type>
      <contributorName>Self</contributorName>
      <payeeName>FOUNDATION TO ERADICATE DUCHENNE, INC.</payeeName>
      <recipientName>SEN. ROY BLUNT AND REP. DEREK KILMER</recipientName>
      <amount>5000.00</amount>
      <date>09/17/2019</date>
    </contribution>
  </contributions>
</CONTRIBUTIONDISCLOSURE>