<?xml version="1.0" encoding="utf-8"?>
<?xml-stylesheet type='text/xsl' href='../../rpt.xslt'?>
<CONTRIBUTIONDISCLOSURE>
  <filerType>O</filerType>
  <organizationName>MAYNARD, COOPER &amp; GALE, P.C.</organizationName>
  <lobbyistPrefix>
  </lobbyistPrefix>
  <lobbyistFirstName>
  </lobbyistFirstName>
  <lobbyistMiddleName>
  </lobbyistMiddleName>
  <lobbyistLastName>
  </lobbyistLastName>
  <lobbyistSuffix>
  </lobbyistSuffix>
  <lobbyistID>
  </lobbyistID>
  <zipext>
  </zipext>
  <contactName>Daniel Wilson</contactName>
  <senateRegID>60116</senateRegID>
  <houseRegID>35353</houseRegID>
  <reportYear>2019</reportYear>
  <reportType>YY</reportType>
  <amendment>False</amendment>
  <comments>
  </comments>
  <signedDate>1/10/2020 3:43:08 PM</signedDate>
  <certifiedcontent>true</certifiedcontent>
  <noContributions>false</noContributions>
  <pacs>
    <pac>
      <name>Maynard Cooper &amp; Gale PC PAC</name>
    </pac>
  </pacs>
  <contributions>
    <contribution>
      <type>FECA</type>
      <contributorName>Maynard Cooper &amp; Gale PC PAC</contributorName>
      <payeeName>Lance Gooden for Congress</payeeName>
      <recipientName>Rep. Lance Gooden</recipientName>
      <amount>1000.00</amount>
      <date>07/03/2019</date>
    </contribution>
    <contribution>
      <type>FECA</type>
      <contributorName>Maynard Cooper &amp; Gale PC PAC</contributorName>
      <payeeName>Alaskans for Dan Sullivan</payeeName>
      <recipientName>Rep. Dan Sullivan</recipientName>
      <amount>1000.00</amount>
      <date>07/03/2019</date>
    </contribution>
    <contribution>
      <type>FECA</type>
      <contributorName>Maynard Cooper &amp; Gale PC PAC</contributorName>
      <payeeName>Manchin for West Virginia</payeeName>
      <recipientName>Sen. Joe Manchin</recipientName>
      <amount>1000.00</amount>
      <date>08/27/2019</date>
    </contribution>
    <contribution>
      <type>FECA</type>
      <contributorName>Maynard Cooper &amp; Gale PC PAC</contributorName>
      <payeeName>Ted Budd for Congress</payeeName>
      <recipientName>Rep. Ted Budd
</recipientName>
      <amount>1000.00</amount>
      <date>07/11/2019</date>
    </contribution>
    <contribution>
      <type>FECA</type>
      <contributorName>Maynard Cooper &amp; Gale PC PAC</contributorName>
      <payeeName>Friends of Jim Clyburn</payeeName>
      <recipientName>Rep. James E. Clyburn</recipientName>
      <amount>1000.00</amount>
      <date>07/11/2019</date>
    </contribution>
    <contribution>
      <type>FECA</type>
      <contributorName>Maynard Cooper &amp; Gale PC PAC</contributorName>
      <payeeName>Team Graham</payeeName>
      <recipientName>Sen. Lindsey Graham</recipientName>
      <amount>1000.00</amount>
      <date>07/11/2019</date>
    </contribution>
    <contribution>
      <type>FECA</type>
      <contributorName>Maynard Cooper &amp; Gale PC PAC</contributorName>
      <payeeName>McConnell Senate Committee</payeeName>
      <recipientName>Sen. Mitch McConnell</recipientName>
      <amount>2500.00</amount>
      <date>07/11/2019</date>
    </contribution>
    <contribution>
      <type>FECA</type>
      <contributorName>Maynard Cooper &amp; Gale PC PAC</contributorName>
      <payeeName>RFW PAC</payeeName>
      <recipientName>RFW PAC / Sen. Roger Wicker</recipientName>
      <amount>1000.00</amount>
      <date>07/23/2019</date>
    </contribution>
    <contribution>
      <type>FECA</type>
      <contributorName>Maynard Cooper &amp; Gale PC PAC</contributorName>
      <payeeName>Perdue Victory, Inc. </payeeName>
      <recipientName>Sen. David Perdue</recipientName>
      <amount>1000.00</amount>
      <date>07/23/2019</date>
    </contribution>
    <contribution>
      <type>FECA</type>
      <contributorName>Maynard Cooper &amp; Gale PC PAC</contributorName>
      <payeeName>Trent Kelly for Congress</payeeName>
      <recipientName>Rep. Trent Kelly</recipientName>
      <amount>1000.00</amount>
      <date>07/23/2019</date>
    </contribution>
    <contribution>
      <type>FECA</type>
      <contributorName>Maynard Cooper &amp; Gale PC PAC</contributorName>
      <payeeName>Citizens for Turner</payeeName>
      <recipientName>Rep. Mike Turner</recipientName>
      <amount>1000.00</amount>
      <date>07/23/2019</date>
    </contribution>
    <contribution>
      <type>FECA</type>
      <contributorName>Maynard Cooper &amp; Gale PC PAC</contributorName>
      <payeeName>Kennedy for Senate</payeeName>
      <recipientName>Sen. John Kennedy</recipientName>
      <amount>1000.00</amount>
      <date>07/23/2019</date>
    </contribution>
    <contribution>
      <type>FECA</type>
      <contributorName>Maynard Cooper &amp; Gale PC PAC</contributorName>
      <payeeName>Butterfield for Congress</payeeName>
      <recipientName>Rep. G. K. Butterfield</recipientName>
      <amount>1000.00</amount>
      <date>07/23/2019</date>
    </contribution>
    <contribution>
      <type>FECA</type>
      <contributorName>Maynard Cooper &amp; Gale PC PAC</contributorName>
      <payeeName>George Holding for Congress</payeeName>
      <recipientName>Rep. George Holding</recipientName>
      <amount>1000.00</amount>
      <date>07/23/2019</date>
    </contribution>
    <contribution>
      <type>FECA</type>
      <contributorName>Maynard Cooper &amp; Gale PC PAC</contributorName>
      <payeeName>Heinrich Victory Fund</payeeName>
      <recipientName>Sen. Martin Heinrich</recipientName>
      <amount>1000.00</amount>
      <date>07/23/2019</date>
    </contribution>
    <contribution>
      <type>FECA</type>
      <contributorName>Maynard Cooper &amp; Gale PC PAC</contributorName>
      <payeeName>Defend America PAC</payeeName>
      <recipientName>Defend America PAC / Sen. Richard Shelby</recipientName>
      <amount>5000.00</amount>
      <date>08/09/2019</date>
    </contribution>
    <contribution>
      <type>FECA</type>
      <contributorName>Maynard Cooper &amp; Gale PC PAC</contributorName>
      <payeeName>Robert Aderholt for Congress</payeeName>
      <recipientName>Rep. Robert Aderholt</recipientName>
      <amount>1500.00</amount>
      <date>08/12/2019</date>
    </contribution>
    <contribution>
      <type>FECA</type>
      <contributorName>Maynard Cooper &amp; Gale PC PAC</contributorName>
      <payeeName>Doug Jones for Senate</payeeName>
      <recipientName>Sen. Doug Jones</recipientName>
      <amount>2500.00</amount>
      <date>08/28/2019</date>
    </contribution>
    <contribution>
      <type>FECA</type>
      <contributorName>Maynard Cooper &amp; Gale PC PAC</contributorName>
      <payeeName>Terri Sewell for Congress</payeeName>
      <recipientName>Rep. Terri Sewell</recipientName>
      <amount>1000.00</amount>
      <date>08/28/2019</date>
    </contribution>
    <contribution>
      <type>FECA</type>
      <contributorName>Maynard Cooper &amp; Gale PC PAC</contributorName>
      <payeeName>Ernst Victory</payeeName>
      <recipientName>Sen. Joni Ernst</recipientName>
      <amount>1000.00</amount>
      <date>09/19/2019</date>
    </contribution>
    <contribution>
      <type>FECA</type>
      <contributorName>Maynard Cooper &amp; Gale PC PAC</contributorName>
      <payeeName>Cooper for Congress</payeeName>
      <recipientName>Rep. Jim Cooper</recipientName>
      <amount>1000.00</amount>
      <date>09/19/2019</date>
    </contribution>
    <contribution>
      <type>FECA</type>
      <contributorName>Maynard Cooper &amp; Gale PC PAC</contributorName>
      <payeeName>Collins for Senator</payeeName>
      <recipientName>Sen. Sue Collins</recipientName>
      <amount>1000.00</amount>
      <date>09/19/2019</date>
    </contribution>
    <contribution>
      <type>FECA</type>
      <contributorName>Maynard Cooper &amp; Gale PC PAC</contributorName>
      <payeeName>Citizens for Turner</payeeName>
      <recipientName>Rep. Mike Turner</recipientName>
      <amount>1000.00</amount>
      <date>09/19/2019</date>
    </contribution>
    <contribution>
      <type>FECA</type>
      <contributorName>Maynard Cooper &amp; Gale PC PAC</contributorName>
      <payeeName>Marsha PAC</payeeName>
      <recipientName>Sen. Marsha Blackburn</recipientName>
      <amount>1500.00</amount>
      <date>09/19/2019</date>
    </contribution>
    <contribution>
      <type>FECA</type>
      <contributorName>Maynard Cooper &amp; Gale PC PAC</contributorName>
      <payeeName>Team McHenry</payeeName>
      <recipientName>Rep. Patrick McHenry
</recipientName>
      <amount>1000.00</amount>
      <date>09/19/2019</date>
    </contribution>
    <contribution>
      <type>FECA</type>
      <contributorName>Maynard Cooper &amp; Gale PC PAC</contributorName>
      <payeeName>Alaskans for Dan Sullivan</payeeName>
      <recipientName>Sen. Dan Sullivan</recipientName>
      <amount>1000.00</amount>
      <date>09/19/2019</date>
    </contribution>
    <contribution>
      <type>FECA</type>
      <contributorName>Maynard Cooper &amp; Gale PC PAC</contributorName>
      <payeeName>Rick W. Allen for Congress</payeeName>
      <recipientName>Rep. Rick W. Allen</recipientName>
      <amount>1000.00</amount>
      <date>09/19/2019</date>
    </contribution>
    <contribution>
      <type>FECA</type>
      <contributorName>Maynard Cooper &amp; Gale PC PAC</contributorName>
      <payeeName>Schatz for Senate</payeeName>
      <recipientName>Sen. Brian Schatz</recipientName>
      <amount>2500.00</amount>
      <date>09/19/2019</date>
    </contribution>
    <contribution>
      <type>FECA</type>
      <contributorName>Maynard Cooper &amp; Gale PC PAC</contributorName>
      <payeeName>Kay Granger Campaign Fund</payeeName>
      <recipientName>Rep. Kay Granger</recipientName>
      <amount>1000.00</amount>
      <date>09/19/2019</date>
    </contribution>
    <contribution>
      <type>FECA</type>
      <contributorName>Maynard Cooper &amp; Gale PC PAC</contributorName>
      <payeeName>John Kennedy for US</payeeName>
      <recipientName>Sen. John Kennedy</recipientName>
      <amount>1000.00</amount>
      <date>09/19/2019</date>
    </contribution>
    <contribution>
      <type>FECA</type>
      <contributorName>Maynard Cooper &amp; Gale PC PAC</contributorName>
      <payeeName>Reclaim America PAC</payeeName>
      <recipientName>Reclaim America PAC / Sen. Marco Rubio</recipientName>
      <amount>1500.00</amount>
      <date>09/19/2019</date>
    </contribution>
    <contribution>
      <type>FECA</type>
      <contributorName>Maynard Cooper &amp; Gale PC PAC</contributorName>
      <payeeName>Texans for Senator John Cornyn</payeeName>
      <recipientName>Sen. John Cornyn</recipientName>
      <amount>1000.00</amount>
      <date>09/19/2019</date>
    </contribution>
    <contribution>
      <type>FECA</type>
      <contributorName>Maynard Cooper &amp; Gale PC PAC</contributorName>
      <payeeName>Friends of Pat Toomey</payeeName>
      <recipientName>Sen. Pat Toomey</recipientName>
      <amount>1000.00</amount>
      <date>09/19/2019</date>
    </contribution>
    <contribution>
      <type>FECA</type>
      <contributorName>Maynard Cooper &amp; Gale PC PAC</contributorName>
      <payeeName>Friends of Pat Toomey</payeeName>
      <recipientName>Sen. Pat Toomey</recipientName>
      <amount>1000.00</amount>
      <date>09/19/2019</date>
    </contribution>
    <contribution>
      <type>FECA</type>
      <contributorName>Maynard Cooper &amp; Gale PC PAC</contributorName>
      <payeeName>Anthony Brown for Congress</payeeName>
      <recipientName>Rep. Anthony Brown</recipientName>
      <amount>1000.00</amount>
      <date>09/24/2019</date>
    </contribution>
    <contribution>
      <type>FECA</type>
      <contributorName>Maynard Cooper &amp; Gale PC PAC</contributorName>
      <payeeName>Chris Coons for Delaware</payeeName>
      <recipientName>Sen. Chris Coons</recipientName>
      <amount>1000.00</amount>
      <date>09/24/2019</date>
    </contribution>
    <contribution>
      <type>FECA</type>
      <contributorName>Maynard Cooper &amp; Gale PC PAC</contributorName>
      <payeeName>Mario Diaz-Balart for Congress</payeeName>
      <recipientName>Rep. Mario Diaz-Balart</recipientName>
      <amount>1000.00</amount>
      <date>09/24/2019</date>
    </contribution>
    <contribution>
      <type>FECA</type>
      <contributorName>Maynard Cooper &amp; Gale PC PAC</contributorName>
      <payeeName>Friends of Bill Posey</payeeName>
      <recipientName>Rep. Bill Posey</recipientName>
      <amount>1000.00</amount>
      <date>09/24/2019</date>
    </contribution>
    <contribution>
      <type>FECA</type>
      <contributorName>Maynard Cooper &amp; Gale PC PAC</contributorName>
      <payeeName>Nita Lowey for Congress</payeeName>
      <recipientName>Rep. Nita Lowey</recipientName>
      <amount>1000.00</amount>
      <date>09/24/2019</date>
    </contribution>
    <contribution>
      <type>FECA</type>
      <contributorName>Maynard Cooper &amp; Gale PC PAC</contributorName>
      <payeeName>David Price for Congress</payeeName>
      <recipientName>Rep. David Price</recipientName>
      <amount>1000.00</amount>
      <date>09/24/2019</date>
    </contribution>
    <contribution>
      <type>FECA</type>
      <contributorName>Maynard Cooper &amp; Gale PC PAC</contributorName>
      <payeeName>Garret Graves for Congress</payeeName>
      <recipientName>Rep. Garret Graves</recipientName>
      <amount>2500.00</amount>
      <date>09/24/2019</date>
    </contribution>
    <contribution>
      <type>FECA</type>
      <contributorName>Maynard Cooper &amp; Gale PC PAC</contributorName>
      <payeeName>Burchett for Congress</payeeName>
      <recipientName>Rep. Tim Burchett</recipientName>
      <amount>1000.00</amount>
      <date>09/24/2019</date>
    </contribution>
    <contribution>
      <type>FECA</type>
      <contributorName>Maynard Cooper &amp; Gale PC PAC</contributorName>
      <payeeName>Perdue Victory Inc. </payeeName>
      <recipientName>Sen. David Perdue</recipientName>
      <amount>1000.00</amount>
      <date>09/24/2019</date>
    </contribution>
    <contribution>
      <type>FECA</type>
      <contributorName>Maynard Cooper &amp; Gale PC PAC</contributorName>
      <payeeName>Aderholt for Congress</payeeName>
      <recipientName>Rep. Robert Aderholt</recipientName>
      <amount>2500.00</amount>
      <date>09/25/2019</date>
    </contribution>
    <contribution>
      <type>FECA</type>
      <contributorName>Maynard Cooper &amp; Gale PC PAC</contributorName>
      <payeeName>Bera for Congress</payeeName>
      <recipientName>Rep. Ami Bera</recipientName>
      <amount>1000.00</amount>
      <date>09/30/2019</date>
    </contribution>
    <contribution>
      <type>FECA</type>
      <contributorName>Maynard Cooper &amp; Gale PC PAC</contributorName>
      <payeeName>Visclosky for Congress</payeeName>
      <recipientName>Rep. Pete Visclosky</recipientName>
      <amount>1000.00</amount>
      <date>09/30/2019</date>
    </contribution>
    <contribution>
      <type>FECA</type>
      <contributorName>Maynard Cooper &amp; Gale PC PAC</contributorName>
      <payeeName>Diana DeGette for Congress</payeeName>
      <recipientName>Rep. Diana DeGette</recipientName>
      <amount>1000.00</amount>
      <date>09/30/2019</date>
    </contribution>
    <contribution>
      <type>FECA</type>
      <contributorName>Maynard Cooper &amp; Gale PC PAC</contributorName>
      <payeeName>Steve Daines for Montana</payeeName>
      <recipientName>Sen. Steve Daines</recipientName>
      <amount>1000.00</amount>
      <date>09/30/2019</date>
    </contribution>
    <contribution>
      <type>FECA</type>
      <contributorName>Maynard Cooper &amp; Gale PC PAC</contributorName>
      <payeeName>Next Century Fund</payeeName>
      <recipientName>Next Century Fund / Sen. Richard Burr</recipientName>
      <amount>1000.00</amount>
      <date>09/30/2019</date>
    </contribution>
    <contribution>
      <type>FECA</type>
      <contributorName>Maynard Cooper &amp; Gale PC PAC</contributorName>
      <payeeName>Denali PAC</payeeName>
      <recipientName>Denali PAC / Sen. Lisa Murkowski</recipientName>
      <amount>1500.00</amount>
      <date>09/30/2019</date>
    </contribution>
    <contribution>
      <type>FECA</type>
      <contributorName>Maynard Cooper &amp; Gale PC PAC</contributorName>
      <payeeName>Team Graham</payeeName>
      <recipientName>Sen. Lindsey Graham</recipientName>
      <amount>1000.00</amount>
      <date>09/30/2019</date>
    </contribution>
    <contribution>
      <type>FECA</type>
      <contributorName>Maynard Cooper &amp; Gale PC PAC</contributorName>
      <payeeName>Rounds for Senate</payeeName>
      <recipientName>Sen. Mike Rounds</recipientName>
      <amount>1000.00</amount>
      <date>09/30/2019</date>
    </contribution>
    <contribution>
      <type>FECA</type>
      <contributorName>Maynard Cooper &amp; Gale PC PAC</contributorName>
      <payeeName>Mo Brooks for Congress</payeeName>
      <recipientName>Rep. Mo Brooks</recipientName>
      <amount>2500.00</amount>
      <date>09/30/2019</date>
    </contribution>
    <contribution>
      <type>FECA</type>
      <contributorName>Maynard Cooper &amp; Gale PC PAC</contributorName>
      <payeeName>Charlie Crist for Congress</payeeName>
      <recipientName>Rep. Charlie Crist</recipientName>
      <amount>1000.00</amount>
      <date>09/30/2019</date>
    </contribution>
    <contribution>
      <type>FECA</type>
      <contributorName>Maynard Cooper &amp; Gale PC PAC</contributorName>
      <payeeName>Ted Cruz Victory Committee</payeeName>
      <recipientName>Sen. Ted Cruz</recipientName>
      <amount>1000.00</amount>
      <date>09/30/2019</date>
    </contribution>
    <contribution>
      <type>FECA</type>
      <contributorName>Maynard Cooper &amp; Gale PC PAC</contributorName>
      <payeeName>Jim Risch for U. S. Senate</payeeName>
      <recipientName>Sen. Jim Risch</recipientName>
      <amount>1000.00</amount>
      <date>09/30/2019</date>
    </contribution>
    <contribution>
      <type>FECA</type>
      <contributorName>Maynard Cooper &amp; Gale PC PAC</contributorName>
      <payeeName>Collins for Congress</payeeName>
      <recipientName>Rep. Doug Collins</recipientName>
      <amount>1000.00</amount>
      <date>11/5/2019</date>
    </contribution>
    <contribution>
      <type>FECA</type>
      <contributorName>Maynard Cooper &amp; Gale PC PAC</contributorName>
      <payeeName>Jim Risch for U.S. Senate</payeeName>
      <recipientName>Sen. Jim Risch</recipientName>
      <amount>1000.00</amount>
      <date>11/5/2019</date>
    </contribution>
    <contribution>
      <type>FECA</type>
      <contributorName>Maynard Cooper &amp; Gale PC PAC</contributorName>
      <payeeName>Kay Granger Campaign Fund</payeeName>
      <recipientName>Rep. Kay Granger</recipientName>
      <amount>1000.00</amount>
      <date>12/17/2019</date>
    </contribution>
    <contribution>
      <type>FECA</type>
      <contributorName>Maynard Cooper &amp; Gale PC PAC</contributorName>
      <payeeName>Alaskans for Dan Sullivan</payeeName>
      <recipientName>Sen. Dan Sullivan</recipientName>
      <amount>1000.00</amount>
      <date>12/17/2019</date>
    </contribution>
    <contribution>
      <type>FECA</type>
      <contributorName>Maynard Cooper &amp; Gale PC PAC</contributorName>
      <payeeName>Team Rick Scott</payeeName>
      <recipientName>Sen. Rick Scott</recipientName>
      <amount>1000.00</amount>
      <date>12/17/2019</date>
    </contribution>
    <contribution>
      <type>FECA</type>
      <contributorName>Maynard Cooper &amp; Gale PC PAC</contributorName>
      <payeeName>Walorski for Congress</payeeName>
      <recipientName>Rep. Jackie Walorski</recipientName>
      <amount>1000.00</amount>
      <date>12/17/2019</date>
    </contribution>
    <contribution>
      <type>FECA</type>
      <contributorName>Maynard Cooper &amp; Gale PC PAC</contributorName>
      <payeeName>Martin Heinrich for Senate</payeeName>
      <recipientName>Sen. Martin Heinrich</recipientName>
      <amount>1000.00</amount>
      <date>12/17/2019</date>
    </contribution>
    <contribution>
      <type>FECA</type>
      <contributorName>Maynard Cooper &amp; Gale PC PAC</contributorName>
      <payeeName>Boozman for Arkansas</payeeName>
      <recipientName>Sen. John Boozman</recipientName>
      <amount>1000.00</amount>
      <date>12/23/2019</date>
    </contribution>
    <contribution>
      <type>FECA</type>
      <contributorName>Maynard Cooper &amp; Gale PC PAC</contributorName>
      <payeeName>People for Patty Murray</payeeName>
      <recipientName>Sen. Patty Murray</recipientName>
      <amount>2000.00</amount>
      <date>12/23/2019</date>
    </contribution>
  </contributions>
</CONTRIBUTIONDISCLOSURE>