<?xml version="1.0" encoding="utf-8"?>
<?xml-stylesheet type='text/xsl' href='../../rpt.xslt'?>
<CONTRIBUTIONDISCLOSURE>
  <filerType>O</filerType>
  <organizationName>American Association of State Colleges and Universities</organizationName>
  <lobbyistPrefix>
  </lobbyistPrefix>
  <lobbyistFirstName>
  </lobbyistFirstName>
  <lobbyistMiddleName>
  </lobbyistMiddleName>
  <lobbyistLastName>
  </lobbyistLastName>
  <lobbyistSuffix>
  </lobbyistSuffix>
  <lobbyistID>
  </lobbyistID>
  <zipext>
  </zipext>
  <contactName>Tonja King</contactName>
  <senateRegID>40020140</senateRegID>
  <houseRegID>39806</houseRegID>
  <reportYear>2019</reportYear>
  <reportType>YY</reportType>
  <amendment>False</amendment>
  <comments>
  </comments>
  <signedDate>1/15/2020 10:55:59 AM</signedDate>
  <certifiedcontent>true</certifiedcontent>
  <noContributions>true</noContributions>
  <pacs>
  </pacs>
  <contributions>
  </contributions>
</CONTRIBUTIONDISCLOSURE>