<?xml version="1.0" encoding="utf-8"?>
<?xml-stylesheet type='text/xsl' href='../../rpt.xslt'?>
<CONTRIBUTIONDISCLOSURE>
  <filerType>O</filerType>
  <organizationName>Susan B Anthony List</organizationName>
  <lobbyistPrefix>
  </lobbyistPrefix>
  <lobbyistFirstName>
  </lobbyistFirstName>
  <lobbyistMiddleName>
  </lobbyistMiddleName>
  <lobbyistLastName>
  </lobbyistLastName>
  <lobbyistSuffix>
  </lobbyistSuffix>
  <lobbyistID>
  </lobbyistID>
  <zipext>
  </zipext>
  <contactName>Emily Buchanan</contactName>
  <senateRegID>400935704</senateRegID>
  <houseRegID>42047</houseRegID>
  <reportYear>2019</reportYear>
  <reportType>YY</reportType>
  <amendment>False</amendment>
  <comments>
  </comments>
  <signedDate>1/30/2020 7:33:21 PM</signedDate>
  <certifiedcontent>true</certifiedcontent>
  <noContributions>false</noContributions>
  <pacs>
    <pac>
      <name>Susan B. Anthony List Candidate Fund</name>
    </pac>
  </pacs>
  <contributions>
    <contribution>
      <type>FECA</type>
      <contributorName>Susan B. Anthony List Candidate Fund</contributorName>
      <payeeName>Virginia Foxx for Congress</payeeName>
      <recipientName>Rep. Virginia Foxx</recipientName>
      <amount>2500.00</amount>
      <date>12/6/2019</date>
    </contribution>
    <contribution>
      <type>FECA</type>
      <contributorName>Susan B. Anthony List Candidate Fund</contributorName>
      <payeeName>Dan Lipinski for Congress</payeeName>
      <recipientName>Rep. Dan Lipinski</recipientName>
      <amount>5000.00</amount>
      <date>12/17/2019</date>
    </contribution>
    <contribution>
      <type>FECA</type>
      <contributorName>Susan B. Anthony List Candidate Fund</contributorName>
      <payeeName>YVETTE4CONGRESS</payeeName>
      <recipientName>Rep. Yvette Herrell</recipientName>
      <amount>1500.00</amount>
      <date>12/20/2019</date>
    </contribution>
    <contribution>
      <type>FECA</type>
      <contributorName>Susan B. Anthony List Candidate Fund</contributorName>
      <payeeName>Claudia for Congress</payeeName>
      <recipientName>Claudia Tenney</recipientName>
      <amount>2500.00</amount>
      <date>12/20/2019</date>
    </contribution>
    <contribution>
      <type>FECA</type>
      <contributorName>Susan B. Anthony List Candidate Fund</contributorName>
      <payeeName>Jessica Taylor for Congress, Inc.</payeeName>
      <recipientName>Jessica Taylor</recipientName>
      <amount>5000.00</amount>
      <date>12/20/2019</date>
    </contribution>
    <contribution>
      <type>FECA</type>
      <contributorName>Susan B. Anthony List Candidate Fund</contributorName>
      <payeeName>Michelle Steel for Congress</payeeName>
      <recipientName>Michelle Steel</recipientName>
      <amount>2500.00</amount>
      <date>12/20/2019</date>
    </contribution>
    <contribution>
      <type>FECA</type>
      <contributorName>Susan B. Anthony List Candidate Fund</contributorName>
      <payeeName>Irina Vilarino for Congress</payeeName>
      <recipientName>Irina Vilarino</recipientName>
      <amount>2500.00</amount>
      <date>12/20/2019</date>
    </contribution>
    <contribution>
      <type>FECA</type>
      <contributorName>Susan B. Anthony List Candidate Fund</contributorName>
      <payeeName>Salazar for Congress</payeeName>
      <recipientName>Maria Salazar</recipientName>
      <amount>2500.00</amount>
      <date>12/20/2019</date>
    </contribution>
    <contribution>
      <type>FECA</type>
      <contributorName>Susan B. Anthony List Candidate Fund</contributorName>
      <payeeName>Beth Van Duyne for Congress</payeeName>
      <recipientName>Beth Van Duyne</recipientName>
      <amount>2500.00</amount>
      <date>12/20/2019</date>
    </contribution>
    <contribution>
      <type>FECA</type>
      <contributorName>Susan B. Anthony List Candidate Fund</contributorName>
      <payeeName>Esther for Congress</payeeName>
      <recipientName>Esther King</recipientName>
      <amount>2500.00</amount>
      <date>12/20/2019</date>
    </contribution>
    <contribution>
      <type>FECA</type>
      <contributorName>Susan B. Anthony List Candidate Fund</contributorName>
      <payeeName>Rounds for Senate</payeeName>
      <recipientName>Sen. Mike Rounds</recipientName>
      <amount>1000.00</amount>
      <date>12/29/2019</date>
    </contribution>
    <contribution>
      <type>FECA</type>
      <contributorName>Susan B. Anthony List Candidate Fund</contributorName>
      <payeeName>Ashley Hinson for Congress</payeeName>
      <recipientName>Ashley Hinson</recipientName>
      <amount>2500.00</amount>
      <date>8/8/2019</date>
    </contribution>
    <contribution>
      <type>FECA</type>
      <contributorName>Susan B. Anthony List Candidate Fund</contributorName>
      <payeeName>Dan Bishop for Congress</payeeName>
      <recipientName>Rep. Dan Bishop</recipientName>
      <amount>2500.00</amount>
      <date>8/26/2019</date>
    </contribution>
    <contribution>
      <type>FECA</type>
      <contributorName>Susan B. Anthony List Candidate Fund</contributorName>
      <payeeName>Liz Cheney for Wyoming</payeeName>
      <recipientName>Rep. Liz Cheney</recipientName>
      <amount>1000.00</amount>
      <date>9/18/2019</date>
    </contribution>
    <contribution>
      <type>FECA</type>
      <contributorName>Susan B. Anthony List Candidate Fund</contributorName>
      <payeeName>Wagner for Congress</payeeName>
      <recipientName>Rep. Ann Wagner</recipientName>
      <amount>1000.00</amount>
      <date>9/19/2019</date>
    </contribution>
    <contribution>
      <type>FECA</type>
      <contributorName>Susan B. Anthony List Candidate Fund</contributorName>
      <payeeName>Friends to Elect Dr. Greg Murphy to Congress</payeeName>
      <recipientName>Rep. Greg Murphy</recipientName>
      <amount>1000.00</amount>
      <date>9/23/2019</date>
    </contribution>
    <contribution>
      <type>FECA</type>
      <contributorName>Susan B. Anthony List Candidate Fund</contributorName>
      <payeeName>Walorski for Congress</payeeName>
      <recipientName>Rep. Jackie Walorski</recipientName>
      <amount>2500.00</amount>
      <date>9/23/2019</date>
    </contribution>
    <contribution>
      <type>FECA</type>
      <contributorName>Susan B. Anthony List Candidate Fund</contributorName>
      <payeeName>Vicky Hartzler for Congress</payeeName>
      <recipientName>Rep. Vicki Hartzler</recipientName>
      <amount>1000.00</amount>
      <date>9/23/2019</date>
    </contribution>
    <contribution>
      <type>FECA</type>
      <contributorName>Susan B. Anthony List Candidate Fund</contributorName>
      <payeeName>Friends of Chris Smith</payeeName>
      <recipientName>Rep. Chris Smith</recipientName>
      <amount>2500.00</amount>
      <date>9/26/2019</date>
    </contribution>
    <contribution>
      <type>FECA</type>
      <contributorName>Susan B. Anthony List Candidate Fund</contributorName>
      <payeeName>Jeanne for Congress</payeeName>
      <recipientName>Jeanne Ives</recipientName>
      <amount>2500.00</amount>
      <date>9/26/2019</date>
    </contribution>
    <contribution>
      <type>FECA</type>
      <contributorName>Susan B. Anthony List Candidate Fund</contributorName>
      <payeeName>Debbie Lesko for Congress</payeeName>
      <recipientName>Rep. Debbie Lesko</recipientName>
      <amount>1000.00</amount>
      <date>11/13/2019</date>
    </contribution>
    <contribution>
      <type>FECA</type>
      <contributorName>Susan B. Anthony List Candidate Fund</contributorName>
      <payeeName>Biggs for Congress</payeeName>
      <recipientName>Rep. Andy Biggs</recipientName>
      <amount>1000.00</amount>
      <date>11/19/2019</date>
    </contribution>
    <contribution>
      <type>FECA</type>
      <contributorName>Susan B. Anthony List Candidate Fund</contributorName>
      <payeeName>Steve Daines for Montana</payeeName>
      <recipientName>Sen. Steve Daines</recipientName>
      <amount>5000.00</amount>
      <date>12/05/2019</date>
    </contribution>
    <contribution>
      <type>FECA</type>
      <contributorName>Susan B. Anthony List Candidate Fund</contributorName>
      <payeeName>Perry for Congress</payeeName>
      <recipientName>Joan Perry</recipientName>
      <amount>498.69</amount>
      <date>7/11/2019</date>
    </contribution>
    <contribution>
      <type>FECA</type>
      <contributorName>Susan B. Anthony List Candidate Fund</contributorName>
      <payeeName>Lindsey Graham for Senate</payeeName>
      <recipientName>Sen. Lindsey Graham</recipientName>
      <amount>463.66</amount>
      <date>7/27/2019</date>
    </contribution>
    <contribution>
      <type>FECA</type>
      <contributorName>Susan B. Anthony List Candidate Fund</contributorName>
      <payeeName>Lindsey Graham for Senate</payeeName>
      <recipientName>Sen. Lindsey Graham</recipientName>
      <amount>2000.00</amount>
      <date>8/31/2019</date>
    </contribution>
    <contribution>
      <type>FECA</type>
      <contributorName>Susan B. Anthony List Candidate Fund</contributorName>
      <payeeName>Greg for Montana</payeeName>
      <recipientName>Rep. Greg Gianforte</recipientName>
      <amount>159.23</amount>
      <date>9/1/2019</date>
    </contribution>
  </contributions>
</CONTRIBUTIONDISCLOSURE>